format_validator/__init__.py
format_validator/format_validator.py
format_validator-0.1.0.dist-info/LICENSE
format_validator-0.1.0.dist-info/METADATA
format_validator-0.1.0.dist-info/WHEEL
format_validator-0.1.0.dist-info/top_level.txt
format_validator-0.1.0.dist-info/RECORD
