Metadata-Version: 2.1
Name: format_validator
Version: 0.1.0
Summary: A simple library to validate emails, phone numbers and dates in various formats
Home-page: https://github.com/Ferref
Author: Ferenc Kovacs
Author-email: kovacsferenc026@gmail.com
Classifier: Programming Language :: Python :: 3
Classifier: License :: OSI Approved :: MIT License
Classifier: Operating System :: OS Independent
Requires-Python: >=3.6
License-File: LICENSE
